[
	{"codigo":"010000","nombre":"Amazonas"},
	{"codigo":"020000","nombre":"Áncash"},
	{"codigo":"030000","nombre":"Apurímac"},
	{"codigo":"040000","nombre":"Arequipa"},
	{"codigo":"050000","nombre":"Ayacucho"},
	{"codigo":"060000","nombre":"Cajamarca"},
	{"codigo":"070000","nombre":"Callao"},
	{"codigo":"080000","nombre":"Cusco"},
	{"codigo":"090000","nombre":"Huancavelica"},
	{"codigo":"100000","nombre":"Huánuco"},
	{"codigo":"110000","nombre":"Ica"},
	{"codigo":"120000","nombre":"Junín"},
	{"codigo":"130000","nombre":"La Libertad"},
	{"codigo":"140000","nombre":"Lambayeque"},
	{"codigo":"150000","nombre":"Lima"},
	{"codigo":"160000","nombre":"Loreto"},
	{"codigo":"170000","nombre":"Madre de Dios"},
	{"codigo":"180000","nombre":"Moquegua"},
	{"codigo":"190000","nombre":"Pasco"},
	{"codigo":"200000","nombre":"Piura"},
	{"codigo":"210000","nombre":"Puno"},
	{"codigo":"220000","nombre":"San Martín"},
	{"codigo":"230000","nombre":"Tacna"},
	{"codigo":"240000","nombre":"Tumbes"},
	{"codigo":"250000","nombre":"Ucayali"}
]
